pascalgt/__init__.py
pascalgt/transformer.py
pascalgt-0.0.2.post2204141209.dist-info/LICENSE
pascalgt-0.0.2.post2204141209.dist-info/METADATA
pascalgt-0.0.2.post2204141209.dist-info/WHEEL
pascalgt-0.0.2.post2204141209.dist-info/top_level.txt
pascalgt-0.0.2.post2204141209.dist-info/zip-safe
pascalgt-0.0.2.post2204141209.dist-info/RECORD
