Metadata-Version: 2.1
Name: pascalgt
Version: 0.0.2-2204141209
Summary: Tool for transform Pascal-VOC xml files and AWS Ground Truth manifest file.
Home-page: https://github.com/DaikiTanak/pascalgt
Author: Daiki Tanaka
Author-email: daiki.yosky@gmail.com
License: MIT
Platform: UNKNOWN
Classifier: Programming Language :: Python :: 3
License-File: LICENSE
Requires-Dist: lxml (==4.6.3)
